[
  {
    "id": "CMSC 441",
    "name": "Design & Analysis of Algorithms",
    "credits": 3,
    "sections": [
      {"section": "01", "instructor": "desJardins, Marie", "days": "MWF", "time": "9:00-9:50am", "location": "ITE 239", "seats_total": 35, "seats_open": 0},
      {"section": "02", "instructor": "Chang, Richard", "days": "TuTh", "time": "11:30am-12:45pm", "location": "ITE 227", "seats_total": 35, "seats_open": 5}
    ]
  },
  {
    "id": "CMSC 447",
    "name": "Software Engineering I",
    "credits": 3,
    "sections": [
      {"section": "01", "instructor": "Squire, Megan", "days": "MWF", "time": "10:00-10:50am", "location": "ITE 101", "seats_total": 40, "seats_open": 12}
    ]
  },
  {
    "id": "CMSC 411",
    "name": "Computer Architecture",
    "credits": 3,
    "sections": [
      {"section": "01", "instructor": "Bourgeois, Arthur", "days": "TuTh", "time": "2:30-3:45pm", "location": "ITE 239", "seats_total": 30, "seats_open": 3}
    ]
  },
  {
    "id": "CMSC 471",
    "name": "Intro to Artificial Intelligence",
    "credits": 3,
    "sections": [
      {"section": "01", "instructor": "Oates, Tim", "days": "MWF", "time": "1:00-1:50pm", "location": "ITE 104", "seats_total": 35, "seats_open": 8}
    ]
  },
  {
    "id": "CMSC 461",
    "name": "Database Management Systems",
    "credits": 3,
    "sections": [
      {"section": "01", "instructor": "Nicholas, Charles", "days": "TuTh", "time": "10:00-11:15am", "location": "ITE 102", "seats_total": 40, "seats_open": 15}
    ]
  },
  {
    "id": "CMSC 481",
    "name": "Computer Networks",
    "credits": 3,
    "sections": [
      {"section": "01", "instructor": "Phatak, Dhananjay", "days": "MWF", "time": "11:00-11:50am", "location": "ITE 237", "seats_total": 30, "seats_open": 7}
    ]
  }
]
